aixnet_beta/__init__.py
aixnet_beta/fm.py
aixnet_beta/meta_llama.py
aixnet_beta/nvidia.py
aixnet_beta-0.2.5.dist-info/METADATA
aixnet_beta-0.2.5.dist-info/WHEEL
aixnet_beta-0.2.5.dist-info/RECORD
