Metadata-Version: 2.1
Name: aixnet-beta
Version: 0.2.5
Summary: The official package of AI-X-Net.
Author: Yiqiao Yin
Author-email: eagle0504@gmail.com
Requires-Python: >=3.10,<4.0
Classifier: Programming Language :: Python :: 3
Classifier: Programming Language :: Python :: 3.10
Classifier: Programming Language :: Python :: 3.11
Classifier: Programming Language :: Python :: 3.12
Requires-Dist: azure-ai-inference (>=1.0.0b4,<2.0.0)
Requires-Dist: openai (>=1.43.0,<2.0.0)
Requires-Dist: requests (>=2.32.3,<3.0.0)
